[
    {
        "名称": "宗谷岬",
        "説明": "日本最北端の地。",
        "都道府県": "北海道",
        "緯度": 45.516667,
        "経度": 141.933333
    },
    {
        "名称": "納沙布岬",
        "説明": "日本本土最東端。",
        "都道府県": "北海道",
        "緯度": 43.383333,
        "経度": 145.816667
    },
    {
        "名称": "襟裳岬",
        "説明": "強風で知られる岬。岩礁が沖へ続く。",
        "都道府県": "北海道",
        "緯度": 41.925000,
        "経度": 143.241667
    },
    {
        "名称": "地球岬",
        "説明": "100mの断崖絶壁。太平洋を一望。",
        "都道府県": "北海道",
        "緯度": 42.300000,
        "経度": 141.000000
    },
    {
        "名称": "神威岬",
        "説明": "積丹半島の先端。積丹ブルーの海。",
        "都道府県": "北海道",
        "緯度": 43.333333,
        "経度": 140.350000
    },
    {
        "名称": "知床岬",
        "説明": "世界自然遺産。船からしか見られない秘境。",
        "都道府県": "北海道",
        "緯度": 44.350000,
        "経度": 145.333333
    },
    {
        "名称": "能取岬",
        "説明": "オホーツク海に突き出た岬。流氷が見える。",
        "都道府県": "北海道",
        "緯度": 44.116667,
        "経度": 144.250000
    },
    {
        "名称": "恵山岬",
        "説明": "活火山恵山の麓にある岬。",
        "都道府県": "北海道",
        "緯度": 41.816667,
        "経度": 141.183333
    },
    {
        "名称": "立待岬",
        "説明": "函館山南東端。津軽海峡を望む。",
        "都道府県": "北海道",
        "緯度": 41.750000,
        "経度": 140.716667
    },
    {
        "名称": "積丹岬",
        "説明": "島武意海岸がある岬。",
        "都道府県": "北海道",
        "緯度": 43.383333,
        "経度": 140.466667
    },
    {
        "名称": "弁慶岬",
        "説明": "寿都町にある岬。",
        "都道府県": "北海道",
        "緯度": 42.816667,
        "経度": 140.366667
    },
    {
        "名称": "落石岬",
        "説明": "根室市のサカイツツジ自生地。",
        "都道府県": "北海道",
        "緯度": 43.166667,
        "経度": 145.516667
    },
    {
        "名称": "霧多布岬",
        "説明": "湯沸岬とも呼ばれる。",
        "都道府県": "北海道",
        "緯度": 43.066667,
        "経度": 145.133333
    },
    {
        "名称": "愛冠岬",
        "説明": "厚岸町。「愛の栄冠」に通じる。",
        "都道府県": "北海道",
        "緯度": 43.033333,
        "経度": 144.833333
    },
    {
        "名称": "チキウ岬",
        "説明": "（地球岬の別表記だが一応）",
        "都道府県": "北海道",
        "緯度": 42.300000,
        "経度": 141.000000
    },
    {
        "名称": "黄金岬",
        "説明": "留萌市の夕日の名所。",
        "都道府県": "北海道",
        "緯度": 43.950000,
        "経度": 141.633333
    },
    {
        "名称": "スコトン岬",
        "説明": "礼文島最北端。",
        "都道府県": "北海道",
        "緯度": 45.466667,
        "経度": 140.966667
    },
    {
        "名称": "仙法志御崎",
        "説明": "利尻島南端。",
        "都道府県": "北海道",
        "緯度": 45.100000,
        "経度": 141.183333
    },
    {
        "名称": "大間崎",
        "説明": "本州最北端。",
        "都道府県": "青森県",
        "緯度": 41.550000,
        "経度": 140.916667
    },
    {
        "名称": "竜飛崎",
        "説明": "津軽半島最北端。風が強い。",
        "都道府県": "青森県",
        "緯度": 41.250000,
        "経度": 140.333333
    },
    {
        "名称": "尻屋崎",
        "説明": "下北半島北東端。寒立馬が放牧されている。",
        "都道府県": "青森県",
        "緯度": 41.433333,
        "経度": 141.466667
    },
    {
        "名称": "入道崎",
        "説明": "男鹿半島北西端。北緯40度線。",
        "都道府県": "秋田県",
        "緯度": 40.000000,
        "経度": 139.700000
    },
    {
        "名称": "魹ヶ崎",
        "説明": "本州最東端の岬。",
        "都道府県": "岩手県",
        "緯度": 39.550000,
        "経度": 142.066667
    },
    {
        "名称": "黒崎",
        "説明": "三陸海岸の断崖。",
        "都道府県": "岩手県",
        "緯度": 40.000000,
        "経度": 141.933333
    },
    {
        "名称": "御崎（唐桑半島）",
        "説明": "リアス式海岸の景勝地。",
        "都道府県": "宮城県",
        "緯度": 38.866667,
        "経度": 141.650000
    },
    {
        "名称": "塩屋埼",
        "説明": "美空ひばりの歌碑と灯台がある。",
        "都道府県": "福島県",
        "緯度": 36.983333,
        "経度": 140.966667
    },
    {
        "名称": "鵜の尾岬",
        "説明": "相馬市。",
        "都道府県": "福島県",
        "緯度": 37.816667,
        "経度": 140.966667
    },
    {
        "名称": "犬吠埼",
        "説明": "関東最東端。初日の出の名所。",
        "都道府県": "千葉県",
        "緯度": 35.700000,
        "経度": 140.866667
    },
    {
        "名称": "野島崎",
        "説明": "房総半島最南端。",
        "都道府県": "千葉県",
        "緯度": 34.900000,
        "経度": 139.883333
    },
    {
        "名称": "洲崎",
        "説明": "房総半島南西端。東京湾の入り口。",
        "都道府県": "千葉県",
        "緯度": 34.966667,
        "経度": 139.750000
    },
    {
        "名称": "太東崎",
        "説明": "いすみ市。",
        "都道府県": "千葉県",
        "緯度": 35.300000,
        "経度": 140.400000
    },
    {
        "名称": "富津岬",
        "説明": "東京湾に突き出た砂州の岬。",
        "都道府県": "千葉県",
        "緯度": 35.300000,
        "経度": 139.800000
    },
    {
        "名称": "大房岬",
        "説明": "南房総国定公園。",
        "都道府県": "千葉県",
        "緯度": 35.050000,
        "経度": 139.816667
    },
    {
        "名称": "刑部岬",
        "説明": "屏風ヶ浦の西端。",
        "都道府県": "千葉県",
        "緯度": 35.700000,
        "経度": 140.716667
    },
    {
        "名称": "観音崎",
        "説明": "日本最古の洋式灯台。",
        "都道府県": "神奈川県",
        "緯度": 35.250000,
        "経度": 139.750000
    },
    {
        "名称": "真鶴岬",
        "説明": "相模湾に突き出た半島。",
        "都道府県": "神奈川県",
        "緯度": 35.133333,
        "経度": 139.150000
    },
    {
        "名称": "剱崎",
        "説明": "三浦半島南東端。",
        "都道府県": "神奈川県",
        "緯度": 35.133333,
        "経度": 139.666667
    },
    {
        "名称": "長者ヶ崎",
        "説明": "葉山町と横須賀市の境。",
        "都道府県": "神奈川県",
        "緯度": 35.250000,
        "経度": 139.566667
    },
    {
        "名称": "稲村ヶ崎",
        "説明": "鎌倉の古戦場。夕日と富士山。",
        "都道府県": "神奈川県",
        "緯度": 35.300000,
        "経度": 139.533333
    },
    {
        "名称": "石廊崎",
        "説明": "伊豆半島最南端。",
        "都道府県": "静岡県",
        "緯度": 34.600000,
        "経度": 138.850000
    },
    {
        "名称": "御前崎",
        "説明": "静岡県最南端。",
        "都道府県": "静岡県",
        "緯度": 34.600000,
        "経度": 138.216667
    },
    {
        "名称": "大瀬崎",
        "説明": "五島列島・福江島の断崖。",
        "都道府県": "長崎県",
        "緯度": 32.616667,
        "経度": 128.600000
    },
    {
        "名称": "城ヶ崎",
        "説明": "（海岸カテゴリで既出だが岬として）",
        "都道府県": "静岡県",
        "緯度": 34.883333,
        "経度": 139.133333
    },
    {
        "名称": "恋人岬",
        "説明": "伊豆市。",
        "都道府県": "静岡県",
        "緯度": 34.850000,
        "経度": 138.750000
    },
    {
        "名称": "黄金崎",
        "説明": "夕日に染まる岩壁。",
        "都道府県": "静岡県",
        "緯度": 34.833333,
        "経度": 138.766667
    },
    {
        "名称": "爪木崎",
        "説明": "水仙の群生地。柱状節理。",
        "都道府県": "静岡県",
        "緯度": 34.650000,
        "経度": 138.983333
    },
    {
        "名称": "伊良湖岬",
        "説明": "渥美半島先端。",
        "都道府県": "愛知県",
        "緯度": 34.583333,
        "経度": 137.016667
    },
    {
        "名称": "羽豆岬",
        "説明": "知多半島先端。",
        "都道府県": "愛知県",
        "緯度": 34.700000,
        "経度": 136.966667
    },
    {
        "名称": "禄剛崎",
        "説明": "能登半島最先端。",
        "都道府県": "石川県",
        "緯度": 37.516667,
        "経度": 137.316667
    },
    {
        "名称": "珠洲岬（聖域の岬）",
        "説明": "パワースポットとして知られる。",
        "都道府県": "石川県",
        "緯度": 37.500000,
        "経度": 137.333333
    },
    {
        "名称": "越前岬",
        "説明": "越前海岸にある岬。水仙。",
        "都道府県": "福井県",
        "緯度": 35.983333,
        "経度": 136.000000
    },
    {
        "名称": "立石岬",
        "説明": "敦賀半島の先端。",
        "都道府県": "福井県",
        "緯度": 35.766667,
        "経度": 136.016667
    },
    {
        "名称": "角田岬",
        "説明": "角田山の麓にある灯台。",
        "都道府県": "新潟県",
        "緯度": 37.816667,
        "経度": 138.833333
    },
    {
        "名称": "大王崎",
        "説明": "絵描きの町として知られる。",
        "都道府県": "三重県",
        "緯度": 34.283333,
        "経度": 136.900000
    },
    {
        "名称": "潮岬",
        "説明": "本州最南端。",
        "都道府県": "和歌山県",
        "緯度": 33.433333,
        "経度": 135.750000
    },
    {
        "名称": "日ノ御埼",
        "説明": "紀伊水道に突出。",
        "都道府県": "和歌山県",
        "緯度": 33.883333,
        "経度": 135.066667
    },
    {
        "名称": "樫野埼",
        "説明": "紀伊大島の東端。トルコ記念館。",
        "都道府県": "和歌山県",
        "緯度": 33.466667,
        "経度": 135.866667
    },
    {
        "名称": "経ヶ岬",
        "説明": "近畿最北端。",
        "都道府県": "京都府",
        "緯度": 35.766667,
        "経度": 135.216667
    },
    {
        "名称": "日和山（城崎）",
        "説明": "日本海を一望。",
        "都道府県": "兵庫県",
        "緯度": 35.650000,
        "経度": 134.816667
    },
    {
        "名称": "日御碕",
        "説明": "日本一高い石造灯台がある。",
        "都道府県": "島根県",
        "緯度": 35.433333,
        "経度": 132.616667
    },
    {
        "名称": "地蔵崎",
        "説明": "島根半島東端。美保関灯台。",
        "都道府県": "島根県",
        "緯度": 35.550000,
        "経度": 133.316667
    },
    {
        "名称": "多古鼻",
        "説明": "島根半島北端。",
        "都道府県": "島根県",
        "緯度": 35.566667,
        "経度": 133.100000
    },
    {
        "名称": "長手岬",
        "説明": "大田市。",
        "都道府県": "島根県",
        "緯度": 35.216667,
        "経度": 132.400000
    },
    {
        "名称": "那沙美崎",
        "説明": "江田島。",
        "都道府県": "広島県",
        "緯度": 34.250000,
        "経度": 132.416667
    },
    {
        "名称": "川尻岬",
        "説明": "本州最北西端。",
        "都道府県": "山口県",
        "緯度": 34.433333,
        "経度": 130.983333
    },
    {
        "名称": "火の山",
        "説明": "関門海峡を望む。",
        "都道府県": "山口県",
        "緯度": 33.966667,
        "経度": 130.950000
    },
    {
        "名称": "室戸岬",
        "説明": "乱礁遊歩道があり、地質遺産が見られる。",
        "都道府県": "高知県",
        "緯度": 33.250000,
        "経度": 134.183333
    },
    {
        "名称": "足摺岬",
        "説明": "四国最南端。断崖絶壁。",
        "都道府県": "高知県",
        "緯度": 32.716667,
        "経度": 133.016667
    },
    {
        "名称": "佐田岬",
        "説明": "日本一細長い半島の先端。",
        "都道府県": "愛媛県",
        "緯度": 33.350000,
        "経度": 132.016667
    },
    {
        "名称": "蒲生田岬",
        "説明": "四国最東端。",
        "都道府県": "徳島県",
        "緯度": 33.833333,
        "経度": 134.750000
    },
    {
        "名称": "竹居観音岬",
        "説明": "四国最北端。",
        "都道府県": "香川県",
        "緯度": 34.400000,
        "経度": 134.133333
    },
    {
        "名称": "高茂岬",
        "説明": "愛媛県最南端。断崖絶壁。",
        "都道府県": "愛媛県",
        "緯度": 32.933333,
        "経度": 132.416667
    },
    {
        "名称": "波戸岬",
        "説明": "玄界灘に突き出た岬。恋人の聖地。",
        "都道府県": "佐賀県",
        "緯度": 33.550000,
        "経度": 129.850000
    },
    {
        "名称": "都井岬",
        "説明": "野生の御崎馬が生息する。",
        "都道府県": "宮崎県",
        "緯度": 31.366667,
        "経度": 131.350000
    },
    {
        "名称": "日向岬（馬ヶ背）",
        "説明": "柱状節理の断崖絶壁。",
        "都道府県": "宮崎県",
        "緯度": 32.433333,
        "経度": 131.683333
    },
    {
        "名称": "佐多岬",
        "説明": "九州本土最南端。",
        "都道府県": "鹿児島県",
        "緯度": 30.983333,
        "経度": 130.650000
    },
    {
        "名称": "長崎鼻",
        "説明": "薩摩半島の最南端。開聞岳の眺望。",
        "都道府県": "鹿児島県",
        "緯度": 31.150000,
        "経度": 130.583333
    },
    {
        "名称": "野母崎",
        "説明": "長崎半島先端。軍艦島が見える。",
        "都道府県": "長崎県",
        "緯度": 32.566667,
        "経度": 129.750000
    },
    {
        "名称": "神崎鼻",
        "説明": "日本本土最西端。",
        "都道府県": "長崎県",
        "緯度": 33.216667,
        "経度": 129.550000
    },
    {
        "名称": "鶴御崎",
        "説明": "九州最東端。",
        "都道府県": "大分県",
        "緯度": 32.933333,
        "経度": 132.083333
    },
    {
        "名称": "関崎",
        "説明": "佐賀関半島の先端。関サバ・関アジ。",
        "都道府県": "大分県",
        "緯度": 33.266667,
        "経度": 131.916667
    },
    {
        "名称": "部埼",
        "説明": "北九州市。",
        "都道府県": "福岡県",
        "緯度": 33.950000,
        "経度": 131.016667
    },
    {
        "名称": "火之神公園（枕崎）",
        "説明": "立神岩が見える。",
        "都道府県": "鹿児島県",
        "緯度": 31.250000,
        "経度": 130.283333
    },
    {
        "名称": "笠沙恵比寿（野間岬）",
        "説明": "（野間岬）薩摩半島西端。",
        "都道府県": "鹿児島県",
        "緯度": 31.416667,
        "経度": 130.133333
    },
    {
        "名称": "喜屋武岬",
        "説明": "沖縄本島最南端。",
        "都道府県": "沖縄県",
        "緯度": 26.083333,
        "経度": 127.666667
    },
    {
        "名称": "辺戸岬",
        "説明": "沖縄本島最北端。",
        "都道府県": "沖縄県",
        "緯度": 26.866667,
        "経度": 128.250000
    },
    {
        "名称": "残波岬",
        "説明": "断崖絶壁と灯台。",
        "都道府県": "沖縄県",
        "緯度": 26.433333,
        "経度": 127.716667
    },
    {
        "名称": "真栄田岬",
        "説明": "ダイビングスポット「青の洞窟」。",
        "都道府県": "沖縄県",
        "緯度": 26.433333,
        "経度": 127.766667
    },
    {
        "名称": "万座毛",
        "説明": "象の鼻の岩。",
        "都道府県": "沖縄県",
        "緯度": 26.500000,
        "経度": 127.850000
    },
    {
        "名称": "知念岬",
        "説明": "南部東海岸。",
        "都道府県": "沖縄県",
        "緯度": 26.166667,
        "経度": 127.816667
    },
    {
        "名称": "東平安名崎",
        "説明": "宮古島の最東端。日本の都市公園百選。",
        "都道府県": "沖縄県",
        "緯度": 24.716667,
        "経度": 125.466667
    },
    {
        "名称": "西平安名崎",
        "説明": "宮古島。",
        "都道府県": "沖縄県",
        "緯度": 24.916667,
        "経度": 125.266667
    },
    {
        "名称": "御神崎",
        "説明": "石垣島西端。夕日の名所。",
        "都道府県": "沖縄県",
        "緯度": 24.450000,
        "経度": 124.066667
    },
    {
        "名称": "平久保崎",
        "説明": "石垣島最北端。",
        "都道府県": "沖縄県",
        "緯度": 24.616667,
        "経度": 124.316667
    },
    {
        "名称": "西崎",
        "説明": "与那国島。日本最西端の岬。",
        "都道府県": "沖縄県",
        "緯度": 24.466667,
        "経度": 122.933333
    },
    {
        "名称": "東崎",
        "説明": "与那国島。与那国馬が放牧されている。",
        "都道府県": "沖縄県",
        "緯度": 24.466667,
        "経度": 123.033333
    },
    {
        "名称": "猫崎",
        "説明": "キューピーに見える半島。",
        "都道府県": "兵庫県",
        "緯度": 35.666667,
        "経度": 134.750000
    },
    {
        "名称": "美保関",
        "説明": "島根半島東端。",
        "都道府県": "島根県",
        "緯度": 35.550000,
        "経度": 133.316667
    },
    {
        "名称": "赤壁",
        "説明": "隠岐・知夫里島の断崖。",
        "都道府県": "島根県",
        "緯度": 36.000000,
        "経度": 133.016667
    },
    {
        "名称": "千畳敷（長門）",
        "説明": "高台にある草原。",
        "都道府県": "山口県",
        "緯度": 34.416667,
        "経度": 131.133333
    }
]